__init__.py
py_multirange.py
py_multirange-0.0.1.dist-info/LICENSE
py_multirange-0.0.1.dist-info/METADATA
py_multirange-0.0.1.dist-info/WHEEL
py_multirange-0.0.1.dist-info/top_level.txt
py_multirange-0.0.1.dist-info/RECORD
