Metadata-Version: 2.1
Name: py-multirange
Version: 0.0.1
Summary: Configurable iterator library for a generalised product of iterators,
Author-email: Purple Elephant <purple.elephant1037@gmail.com>
Project-URL: Homepage, https://github.com/purple-elephant1037/py_multirange
Project-URL: Test code, https://github.com/purple-elephant1037/
Classifier: Programming Language :: Python :: 3
Classifier: License :: OSI Approved :: MIT License
Classifier: Operating System :: OS Independent
Classifier: Topic :: Software Development :: Testing
Classifier: Topic :: Software Development :: Libraries
Classifier: Topic :: Utilities
Requires-Python: >=3.7
License-File: LICENSE
